hoppr/__init__.py
hoppr/__main__.py
hoppr/base_plugins/__init__.py
hoppr/base_plugins/collector.py
hoppr/base_plugins/hoppr.py
hoppr/base_plugins/py.typed
hoppr/cli/__init__.py
hoppr/cli/bundle.py
hoppr/cli/experimental/__init__.py
hoppr/cli/experimental/py.typed
hoppr/cli/experimental/validate.py
hoppr/cli/generate.py
hoppr/cli/layout.py
hoppr/cli/merge.py
hoppr/cli/options.py
hoppr/cli/py.typed
hoppr/cli/validate.py
hoppr/constants.py
hoppr/core_plugins/__init__.py
hoppr/core_plugins/bundle_tar.py
hoppr/core_plugins/collect_apt_plugin.py
hoppr/core_plugins/collect_cargo_plugin.py
hoppr/core_plugins/collect_dnf_plugin.py
hoppr/core_plugins/collect_docker_plugin.py
hoppr/core_plugins/collect_gem_plugin.py
hoppr/core_plugins/collect_git_plugin.py
hoppr/core_plugins/collect_golang_plugin.py
hoppr/core_plugins/collect_helm_plugin.py
hoppr/core_plugins/collect_maven_plugin.py
hoppr/core_plugins/collect_nexus_search.py
hoppr/core_plugins/collect_npm_plugin.py
hoppr/core_plugins/collect_nuget_plugin.py
hoppr/core_plugins/collect_pypi_plugin.py
hoppr/core_plugins/collect_raw_plugin.py
hoppr/core_plugins/collect_yum_plugin.py
hoppr/core_plugins/composite_collector.py
hoppr/core_plugins/delta_sbom.py
hoppr/core_plugins/oras_bundle.py
hoppr/core_plugins/oras_registry.py
hoppr/core_plugins/py.typed
hoppr/core_plugins/report_generator/__init__.py
hoppr/core_plugins/report_generator/assets/hoppr_hippo.png
hoppr/core_plugins/report_generator/report_generator.py
hoppr/core_plugins/report_generator/scripts/bootstrap.min.js
hoppr/core_plugins/report_generator/scripts/custom.js
hoppr/core_plugins/report_generator/styles/bootstrap.min.css
hoppr/core_plugins/report_generator/styles/custom.css
hoppr/core_plugins/report_generator/templates/component_card.jinja2
hoppr/core_plugins/report_generator/templates/general_summary.jinja2
hoppr/core_plugins/report_generator/templates/index.jinja2
hoppr/exceptions.py
hoppr/in_toto.py
hoppr/logger.py
hoppr/logger.pyi
hoppr/main.py
hoppr-1.14.1.dist-info/LICENSE
hoppr-1.14.1.dist-info/METADATA
hoppr-1.14.1.dist-info/WHEEL
hoppr-1.14.1.dist-info/entry_points.txt
hoppr-1.14.1.dist-info/RECORD
